criteria/__init__.py
criteria/clip_loss.py
criteria/id_loss.py
criteria/configs/config.yaml
criteria/lpips/__init__.py
criteria/lpips/lpips.py
criteria/lpips/networks.py
criteria/lpips/utils.py
criteria/models/__init__.py
criteria/models/facenet.py
criteria/models/helpers.py
criteria/models/ir152.py
criteria/models/irse.py
criteria/models/model_irse.py
criteria/utils/download.py
criteria/utils/paths.py
criteria-0.1.7.dist-info/LICENSE
criteria-0.1.7.dist-info/METADATA
criteria-0.1.7.dist-info/WHEEL
criteria-0.1.7.dist-info/top_level.txt
criteria-0.1.7.dist-info/RECORD
