Metadata-Version: 2.1
Name: criteria
Version: 0.1.7
Summary: Deep learning loss functions and models for image similarity
Author-email: Minh-Ha Le <minhha.x89@gmail.com>
License: MIT
Project-URL: Homepage, https://github.com/minha12/criteria
Requires-Python: >=3.6
License-File: LICENSE
Requires-Dist: torch
Requires-Dist: gdown
Requires-Dist: numpy
Requires-Dist: hydra-core
Requires-Dist: omegaconf
Requires-Dist: openai-clip
Requires-Dist: torchvision<0.20.0,>=0.2.1
Requires-Dist: pillow<10.1.0,>=8.3.2
Requires-Dist: scipy<1.11.0,>=1.0.1
Requires-Dist: absl-py
Requires-Dist: google-auth-oauthlib<1.1,>=0.5
Requires-Dist: grpcio
Requires-Dist: tensorboard-data-server
